[
  {
    "product_url": "https://www.family.co.jp/goods/omusubi/0416474.html",
    "product_name": "【関東】ごちむすび　かにめし",
    "product_price": 298,
    "product_date": "2024.4.23",
    "product_image": "https://www.family.co.jp/content/dam/family/goods/0416474.jpg"
  },
  {
    "product_url": "https://www.family.co.jp/goods/omusubi/0416467.html",
    "product_name": "ごちむすび　いくらと炙りたらこ",
    "product_price": 290,
    "product_date": "2024.4.23",
    "product_image": "https://www.family.co.jp/content/dam/family/goods/0416467.jpg"
  },
  {
    "product_url": "https://www.family.co.jp/goods/omusubi/0416290.html",
    "product_name": "ごちむすび　鮭はらみ",
    "product_price": 248,
    "product_date": "2024.4.23",
    "product_image": "https://www.family.co.jp/content/dam/family/goods/0416290.jpg"
  },
  {
    "product_url": "https://www.family.co.jp/goods/obento/0616584.html",
    "product_name": "洋風ミックス弁当（デミハンバーグ）",
    "product_price": 538,
    "product_date": "2024.4.23",
    "product_image": "https://www.family.co.jp/content/dam/family/goods/0616584.jpg"
  },
  {
    "product_url": "https://www.family.co.jp/goods/obento/0616591.html",
    "product_name": "大盛ごはん！チキンカツ弁当",
    "product_price": 638,
    "product_date": "2024.4.23",
    "product_image": "https://www.family.co.jp/content/dam/family/goods/0616591.jpg"
  },
  {
    "product_url": "https://www.family.co.jp/goods/obento/0730631.html",
    "product_name": "にんにく醤油香る牛焼肉&ガーリックライス",
    "product_price": 598,
    "product_date": "2024.4.23",
    "product_image": "https://www.family.co.jp/content/dam/family/goods/0730631.jpg"
  },
  {
    "product_url": "https://www.family.co.jp/goods/obento/0730648.html",
    "product_name": "特製和風おろしソースの鉄板焼ビーフハンバーグ弁当",
    "product_price": 598,
    "product_date": "2024.4.23",
    "product_image": "https://www.family.co.jp/content/dam/family/goods/0730648.jpg"
  },
  {
    "product_url": "https://www.family.co.jp/goods/sushi/0514651.html",
    "product_name": "肉山監修　2種のキンパッ！",
    "product_price": 498,
    "product_date": "2024.4.23",
    "product_image": "https://www.family.co.jp/content/dam/family/goods/0514651.jpg"
  },
  {
    "product_url": "https://www.family.co.jp/goods/sushi/0515061.html",
    "product_name": "ピリ辛高菜いなり寿司",
    "product_price": 150,
    "product_date": "2024.4.23",
    "product_image": "https://www.family.co.jp/content/dam/family/goods/0515061.jpg"
  },
  {
    "product_url": "https://www.family.co.jp/goods/sandwich/0920322.html",
    "product_name": "【関東】植物生まれのチーズとケールのサラダラップ",
    "product_price": 398,
    "product_date": "2024.4.23",
    "product_image": "https://www.family.co.jp/content/dam/family/goods/0920322.jpg"
  },
  {
    "product_url": "https://www.family.co.jp/goods/bread/1532371.html",
    "product_name": "生コッペパン（トリプルチョコ）",
    "product_price": 168,
    "product_date": "2024.4.23",
    "product_image": "https://www.family.co.jp/content/dam/family/goods/1532371.jpg"
  },
  {
    "product_url": "https://www.family.co.jp/goods/bread/1510997.html",
    "product_name": "ハムクロワッサンサンド3個入",
    "product_price": 268,
    "product_date": "2024.4.23",
    "product_image": "https://www.family.co.jp/content/dam/family/goods/1510997.jpg"
  },
  {
    "product_url": "https://www.family.co.jp/goods/bread/1511871.html",
    "product_name": "生スコーン6個入（レモン）",
    "product_price": 185,
    "product_date": "2024.4.23",
    "product_image": "https://www.family.co.jp/content/dam/family/goods/1511871.jpg"
  },
  {
    "product_url": "https://www.family.co.jp/goods/bread/1522105.html",
    "product_name": "ホットサンド（てりやきチキン&たまご）",
    "product_price": 168,
    "product_date": "2024.4.23",
    "product_image": "https://www.family.co.jp/content/dam/family/goods/1522105.jpg"
  },
  {
    "product_url": "https://www.family.co.jp/goods/bread/1535549.html",
    "product_name": "ソイデニッシュ（シナモンアップル&レーズン）",
    "product_price": 158,
    "product_date": "2024.4.23",
    "product_image": "https://www.family.co.jp/content/dam/family/goods/1535549.jpg"
  },
  {
    "product_url": "https://www.family.co.jp/goods/noodle/0810241.html",
    "product_name": "石臼挽きそば粉使用　大盛冷しぶっかけそば",
    "product_price": 538,
    "product_date": "2024.4.23",
    "product_image": "https://www.family.co.jp/content/dam/family/goods/0810241.jpg"
  },
  {
    "product_url": "https://www.family.co.jp/goods/pasta/0820134.html",
    "product_name": "冷たいパスタ　ベーコンとトマト",
    "product_price": 538,
    "product_date": "2024.4.23",
    "product_image": "https://www.family.co.jp/content/dam/family/goods/0820134.jpg"
  },
  {
    "product_url": "https://www.family.co.jp/goods/pasta/0821520.html",
    "product_name": "冷たいパスタ　蒸し鶏のゆず胡椒ぽん酢",
    "product_price": 538,
    "product_date": "2024.4.23",
    "product_image": "https://www.family.co.jp/content/dam/family/goods/0821520.jpg"
  },
  {
    "product_url": "https://www.family.co.jp/goods/salad/1221374.html",
    "product_name": "トマトとバジルポテトのパスタサラダ",
    "product_price": 398,
    "product_date": "2024.4.23",
    "product_image": "https://www.family.co.jp/content/dam/family/goods/1221374.jpg"
  },
  {
    "product_url": "https://www.family.co.jp/goods/salad/1211689.html",
    "product_name": "カニカマとマカロニのサラダ",
    "product_price": 248,
    "product_date": "2024.4.23",
    "product_image": "https://www.family.co.jp/content/dam/family/goods/1211689.jpg"
  },
  {
    "product_url": "https://www.family.co.jp/goods/sidedishes/1161113.html",
    "product_name": "ミートソースで食べるポテト（ペンネ入り）",
    "product_price": 468,
    "product_date": "2024.4.23",
    "product_image": "https://www.family.co.jp/content/dam/family/goods/1161113.jpg"
  },
  {
    "product_url": "https://www.family.co.jp/goods/sidedishes/1161120.html",
    "product_name": "2種の花椒の本格痺辛麻婆豆腐",
    "product_price": 398,
    "product_date": "2024.4.23",
    "product_image": "https://www.family.co.jp/content/dam/family/goods/1161120.jpg"
  },
  {
    "product_url": "https://www.family.co.jp/goods/sidedishes/1181746.html",
    "product_name": "野菜と食べる豚肉おろし柚子ぽん酢だれ",
    "product_price": 498,
    "product_date": "2024.4.23",
    "product_image": "https://www.family.co.jp/content/dam/family/goods/1181746.jpg"
  },
  {
    "product_url": "https://www.family.co.jp/goods/sidedishes/1132281.html",
    "product_name": "燻しベーコンのポテトサラダ（マスタード風味）",
    "product_price": 268,
    "product_date": "2024.4.23",
    "product_image": "https://www.family.co.jp/content/dam/family/goods/1132281.jpg"
  },
  {
    "product_url": "https://www.family.co.jp/goods/sidedishes/1132311.html",
    "product_name": "カニカマとキャベツのからしマヨ",
    "product_price": 238,
    "product_date": "2024.4.23",
    "product_image": "https://www.family.co.jp/content/dam/family/goods/1132311.jpg"
  },
  {
    "product_url": "https://www.family.co.jp/goods/sidedishes/1132397.html",
    "product_name": "キャベツとツナのマヨ和えサラダ",
    "product_price": 248,
    "product_date": "2024.4.23",
    "product_image": "https://www.family.co.jp/content/dam/family/goods/1132397.jpg"
  },
  {
    "product_url": "https://www.family.co.jp/goods/deli/1020137.html",
    "product_name": "雑穀入り　沖縄県産もずくと蒸し鶏のだし茶漬け",
    "product_price": 398,
    "product_date": "2024.4.23",
    "product_image": "https://www.family.co.jp/content/dam/family/goods/1020137.jpg"
  },
  {
    "product_url": "https://www.family.co.jp/goods/deli/1020199.html",
    "product_name": "【関東・東海】豆腐と玉子の辛旨スープ",
    "product_price": 398,
    "product_date": "2024.4.23",
    "product_image": "https://www.family.co.jp/content/dam/family/goods/1020199.jpg"
  },
  {
    "product_url": "https://www.family.co.jp/goods/deli/1031133.html",
    "product_name": "魚介の旨み海老トマトクリームドリア",
    "product_price": 498,
    "product_date": "2024.4.23",
    "product_image": "https://www.family.co.jp/content/dam/family/goods/1031133.jpg"
  },
  {
    "product_url": "https://www.family.co.jp/goods/deli/1063042.html",
    "product_name": "豚玉お好み焼&焼そば",
    "product_price": 430,
    "product_date": "2024.4.23",
    "product_image": "https://www.family.co.jp/content/dam/family/goods/1063042.jpg"
  },
  {
    "product_url": "https://www.family.co.jp/goods/chilleddaily/2110684.html",
    "product_name": "【北海道・東北・関東】担々スープで食べる糖質0gこんにゃく麺",
    "product_price": 238,
    "product_date": "2024.4.23",
    "product_image": "https://www.family.co.jp/content/dam/family/goods/2110684.jpg"
  },
  {
    "product_url": "https://www.family.co.jp/goods/chilleddaily/2110431.html",
    "product_name": "【北海道・東北・関東】めんつゆで食べる糖質0gこんにゃく麺",
    "product_price": 238,
    "product_date": "2024.4.23",
    "product_image": "https://www.family.co.jp/content/dam/family/goods/2110431.jpg"
  },
  {
    "product_url": "https://www.family.co.jp/goods/chilleddaily/2210292.html",
    "product_name": "おしんこ盛り合わせ",
    "product_price": 220,
    "product_date": "2024.4.23",
    "product_image": "https://www.family.co.jp/content/dam/family/goods/2210292.jpg"
  },
  {
    "product_url": "https://www.family.co.jp/goods/friedfoods/0250429.html",
    "product_name": "ファミチキ（旨塩だれ）",
    "product_price": 240,
    "product_date": "2024.4.23",
    "product_image": "https://www.family.co.jp/content/dam/family/goods/0250429.jpg"
  },
  {
    "product_url": "https://www.family.co.jp/goods/dessert/1944044.html",
    "product_name": "チョコバナナクレープ",
    "product_price": 348,
    "product_date": "2024.4.23",
    "product_image": "https://www.family.co.jp/content/dam/family/goods/1944044.jpg"
  },
  {
    "product_url": "https://www.family.co.jp/goods/dessert/1947021.html",
    "product_name": "黒みつと味わうクリームわらび餅",
    "product_price": 260,
    "product_date": "2024.4.23",
    "product_image": "https://www.family.co.jp/content/dam/family/goods/1947021.jpg"
  },
  {
    "product_url": "https://www.family.co.jp/goods/dessert/1940893.html",
    "product_name": "植物生まれのティラミス",
    "product_price": 328,
    "product_date": "2024.4.23",
    "product_image": "https://www.family.co.jp/content/dam/family/goods/1940893.jpg"
  },
  {
    "product_url": "https://www.family.co.jp/goods/dessert/1930207.html",
    "product_name": "濃い超満足みかん",
    "product_price": 358,
    "product_date": "2024.4.23",
    "product_image": "https://www.family.co.jp/content/dam/family/goods/1930207.jpg"
  },
  {
    "product_url": "https://www.family.co.jp/goods/dessert/1952995.html",
    "product_name": "星のカービィまんまる焼き",
    "product_price": 230,
    "product_date": "2024.4.23",
    "product_image": "https://www.family.co.jp/content/dam/family/goods/1952995.jpg"
  },
  {
    "product_url": "https://www.family.co.jp/goods/baked_sweets/1320848.html",
    "product_name": "植物生まれのレーズンサンド（全粒粉入り）",
    "product_price": 208,
    "product_date": "2024.4.23",
    "product_image": "https://www.family.co.jp/content/dam/family/goods/1320848.jpg"
  },
  {
    "product_url": "https://www.family.co.jp/goods/roll/0736008.html",
    "product_name": "【大阪府】だし巻玉子&焼鳥弁当",
    "product_price": 578,
    "product_date": "2024.4.23",
    "product_image": "https://www.family.co.jp/content/dam/family/goods/0736008.jpg"
  },
  {
    "product_url": "https://www.family.co.jp/goods/roll/0415026.html",
    "product_name": "【東海】ゆかりごはんおむすび",
    "product_price": 115,
    "product_date": "2024.4.23",
    "product_image": "https://www.family.co.jp/content/dam/family/goods/0415026.jpg"
  },
  {
    "product_url": "https://www.family.co.jp/goods/roll/1037012.html",
    "product_name": "【四国】ミニお好み焼",
    "product_price": 230,
    "product_date": "2024.4.23",
    "product_image": "https://www.family.co.jp/content/dam/family/goods/1037012.jpg"
  },
  {
    "product_url": "https://www.family.co.jp/goods/roll/0411998.html",
    "product_name": "【東京都・神奈川県の一部】植物生まれのソイツナ&マヨソースおむすび",
    "product_price": 176,
    "product_date": "2024.4.23",
    "product_image": "https://www.family.co.jp/content/dam/family/goods/0411998.jpg"
  },
  {
    "product_url": "https://www.family.co.jp/goods/roll/1063035.html",
    "product_name": "【北海道・東北】豚玉お好み焼&いか玉お好み焼",
    "product_price": 550,
    "product_date": "2024.4.23",
    "product_image": "https://www.family.co.jp/content/dam/family/goods/1063035.jpg"
  },
  {
    "product_url": "https://www.family.co.jp/goods/processed_foods/3812211.html",
    "product_name": "Lab Q かけ醤油らぁ麺",
    "product_price": 268,
    "product_date": "2024.4.23",
    "product_image": "https://www.family.co.jp/content/dam/family/goods/3812211.jpg"
  },
  {
    "product_url": "https://www.family.co.jp/goods/snack/4724773.html",
    "product_name": "サングリーン　オクラのまんまコンソメ風味",
    "product_price": 238,
    "product_date": "2024.4.23",
    "product_image": "https://www.family.co.jp/content/dam/family/goods/4724773.jpg"
  },
  {
    "product_url": "https://www.family.co.jp/goods/snack/4727347.html",
    "product_name": "素材の甘みをぎゅっと半生ドライもも",
    "product_price": 290,
    "product_date": "2024.4.23",
    "product_image": "https://www.family.co.jp/content/dam/family/goods/4727347.jpg"
  },
  {
    "product_url": "https://www.family.co.jp/goods/snack/5013111.html",
    "product_name": "ホタヒカ　えびヤンニョム味",
    "product_price": 398,
    "product_date": "2024.4.23",
    "product_image": "https://www.family.co.jp/content/dam/family/goods/5013111.jpg"
  },
  {
    "product_url": "https://www.family.co.jp/goods/snack/5013234.html",
    "product_name": "ホタヒカ　レモンチップス",
    "product_price": 398,
    "product_date": "2024.4.23",
    "product_image": "https://www.family.co.jp/content/dam/family/goods/5013234.jpg"
  },
  {
    "product_url": "https://www.family.co.jp/goods/snack/5020645.html",
    "product_name": "ホタヒカ　柿の種焼チーズ",
    "product_price": 328,
    "product_date": "2024.4.23",
    "product_image": "https://www.family.co.jp/content/dam/family/goods/5020645.jpg"
  },
  {
    "product_url": "https://www.family.co.jp/goods/snack/4722762.html",
    "product_name": "クリート　学研の図鑑LIVE 恐竜グミ",
    "product_price": 198,
    "product_date": "2024.4.23",
    "product_image": "https://www.family.co.jp/content/dam/family/goods/4722762.jpg"
  },
  {
    "product_url": "https://www.family.co.jp/goods/snack/4725619.html",
    "product_name": "素材の甘みをぎゅっと半生ドライりんご",
    "product_price": 290,
    "product_date": "2024.4.23",
    "product_image": "https://www.family.co.jp/content/dam/family/goods/4725619.jpg"
  },
  {
    "product_url": "https://www.family.co.jp/goods/snack/4729617.html",
    "product_name": "トロピカルな香りきわだつドライパッションフルーツ",
    "product_price": 248,
    "product_date": "2024.4.23",
    "product_image": "https://www.family.co.jp/content/dam/family/goods/4729617.jpg"
  },
  {
    "product_url": "https://www.family.co.jp/goods/snack/4749233.html",
    "product_name": "芥川製菓　たっぷりチョコのチョコプレッツェル",
    "product_price": 298,
    "product_date": "2024.4.23",
    "product_image": "https://www.family.co.jp/content/dam/family/goods/4749233.jpg"
  },
  {
    "product_url": "https://www.family.co.jp/goods/snack/4749301.html",
    "product_name": "芥川製菓　カカオ香るビターチョコクランチ",
    "product_price": 290,
    "product_date": "2024.4.23",
    "product_image": "https://www.family.co.jp/content/dam/family/goods/4749301.jpg"
  },
  {
    "product_url": "https://www.family.co.jp/goods/snack/4749356.html",
    "product_name": "芥川製菓　こだわりチョコ仕立てノワールカフェショコラ",
    "product_price": 290,
    "product_date": "2024.4.23",
    "product_image": "https://www.family.co.jp/content/dam/family/goods/4749356.jpg"
  },
  {
    "product_url": "https://www.family.co.jp/goods/snack/4822318.html",
    "product_name": "ごま3,000粒を使用したパリッとごません",
    "product_price": 165,
    "product_date": "2024.4.23",
    "product_image": "https://www.family.co.jp/content/dam/family/goods/4822318.jpg"
  },
  {
    "product_url": "https://www.family.co.jp/goods/snack/4913597.html",
    "product_name": "カルビー　ポテトチップス　ぎゅっと素材のおいしさ　たまねぎのうまみ味",
    "product_price": 171,
    "product_date": "2024.4.23",
    "product_image": "https://www.family.co.jp/content/dam/family/goods/4913597.jpg"
  },
  {
    "product_url": "https://www.family.co.jp/goods/snack/5011117.html",
    "product_name": "ホタヒカ　燻製アジ",
    "product_price": 328,
    "product_date": "2024.4.23",
    "product_image": "https://www.family.co.jp/content/dam/family/goods/5011117.jpg"
  },
  {
    "product_url": "https://www.family.co.jp/goods/snack/5011216.html",
    "product_name": "【関東】サクッとピリ辛さきいか天",
    "product_price": 378,
    "product_date": "2024.4.23",
    "product_image": "https://www.family.co.jp/content/dam/family/goods/5011216.jpg"
  },
  {
    "product_url": "https://www.family.co.jp/goods/snack/5013173.html",
    "product_name": "ホタヒカ　いか天トリュフ味",
    "product_price": 228,
    "product_date": "2024.4.23",
    "product_image": "https://www.family.co.jp/content/dam/family/goods/5013173.jpg"
  },
  {
    "product_url": "https://www.family.co.jp/goods/snack/5013227.html",
    "product_name": "ホタヒカ　山椒サラミ",
    "product_price": 398,
    "product_date": "2024.4.23",
    "product_image": "https://www.family.co.jp/content/dam/family/goods/5013227.jpg"
  },
  {
    "product_url": "https://www.family.co.jp/goods/snack/5013241.html",
    "product_name": "ホタヒカ　干し梅バニラ",
    "product_price": 268,
    "product_date": "2024.4.23",
    "product_image": "https://www.family.co.jp/content/dam/family/goods/5013241.jpg"
  },
  {
    "product_url": "https://www.family.co.jp/goods/snack/5021666.html",
    "product_name": "ホタヒカ　備長炭カシュー",
    "product_price": 328,
    "product_date": "2024.4.23",
    "product_image": "https://www.family.co.jp/content/dam/family/goods/5021666.jpg"
  },
  {
    "product_url": "https://www.family.co.jp/goods/snack/5021680.html",
    "product_name": "ホタヒカ　マカダミアナッツ梅昆布味",
    "product_price": 398,
    "product_date": "2024.4.23",
    "product_image": "https://www.family.co.jp/content/dam/family/goods/5021680.jpg"
  },
  {
    "product_url": "https://www.family.co.jp/goods/snack/5021697.html",
    "product_name": "ホタヒカ　チョコナッツミックス",
    "product_price": 328,
    "product_date": "2024.4.23",
    "product_image": "https://www.family.co.jp/content/dam/family/goods/5021697.jpg"
  },
  {
    "product_url": "https://www.family.co.jp/goods/snack/5013203.html",
    "product_name": "ホタヒカ　削りチーズガーリックハーブ",
    "product_price": 228,
    "product_date": "2024.4.23",
    "product_image": "https://www.family.co.jp/content/dam/family/goods/5013203.jpg"
  },
  {
    "product_url": "https://www.family.co.jp/goods/snack/5021673.html",
    "product_name": "【北海道・東北・関東】ホタヒカ　ジャイアントコーン梅昆布味",
    "product_price": 268,
    "product_date": "2024.4.23",
    "product_image": "https://www.family.co.jp/content/dam/family/goods/5021673.jpg"
  },
  {
    "product_url": "https://www.family.co.jp/goods/drink/1730494.html",
    "product_name": "のむヨーグルトマンゴー",
    "product_price": 168,
    "product_date": "2024.4.23",
    "product_image": "https://www.family.co.jp/content/dam/family/goods/1730494.jpg"
  },
  {
    "product_url": "https://www.family.co.jp/goods/alcohol/5511907.html",
    "product_name": "一ノ蔵　本醸造辛口　720ml",
    "product_price": 58,
    "product_date": "2024.4.23",
    "product_image": "https://www.family.co.jp/content/dam/family/goods/5511907.jpg"
  },
  {
    "product_url": "https://www.family.co.jp/goods/alcohol/5832323.html",
    "product_name": "サントリー　山崎蒸溜所貯蔵梅酒ブレンドソーダ割り　350ml",
    "product_price": 218,
    "product_date": "2024.4.23",
    "product_image": "https://www.family.co.jp/content/dam/family/goods/5832323.jpg"
  },
  {
    "product_url": "https://www.family.co.jp/goods/frozen_foods/3533277.html",
    "product_name": "北海道産じゃがいものやみつきポテト　のり塩味",
    "product_price": 190,
    "product_date": "2024.4.23",
    "product_image": "https://www.family.co.jp/content/dam/family/goods/3533277.jpg"
  },
  {
    "product_url": "https://www.family.co.jp/goods/ice/3442944.html",
    "product_name": "北海道産練乳のいちご氷バー",
    "product_price": 120,
    "product_date": "2024.4.23",
    "product_image": "https://www.family.co.jp/content/dam/family/goods/3442944.jpg"
  },
  {
    "product_url": "https://www.family.co.jp/goods/daily_necessities/6940089.html",
    "product_name": "水の【激落ちくん】®　アルカリ電解水スプレー",
    "product_price": 300,
    "product_date": "2024.4.23",
    "product_image": "https://www.family.co.jp/content/dam/family/goods/6940089.jpg"
  },
  {
    "product_url": "https://www.family.co.jp/goods/daily_necessities/7121449.html",
    "product_name": "水の【激落ちくん】®　IH&ガスコンロ用シート　20枚入",
    "product_price": 110,
    "product_date": "2024.4.23",
    "product_image": "https://www.family.co.jp/content/dam/family/goods/7121449.jpg"
  },
  {
    "product_url": "https://www.family.co.jp/goods/daily_necessities/7121456.html",
    "product_name": "水の【激落ちくん】®　電子レンジ&冷蔵庫用シート　20枚入",
    "product_price": 110,
    "product_date": "2024.4.23",
    "product_image": "https://www.family.co.jp/content/dam/family/goods/7121456.jpg"
  },
  {
    "product_url": "https://www.family.co.jp/goods/cw/7810732.html",
    "product_name": "シャープペンシル　グレー（1本）",
    "product_price": 198,
    "product_date": "2024.4.23",
    "product_image": "https://www.family.co.jp/content/dam/family/goods/7810732.jpg"
  },
  {
    "product_url": "https://www.family.co.jp/goods/cw/7820106.html",
    "product_name": "ハサミ（1本）",
    "product_price": 748,
    "product_date": "2024.4.23",
    "product_image": "https://www.family.co.jp/content/dam/family/goods/7820106.jpg"
  },
  {
    "product_url": "https://www.family.co.jp/goods/cw/7820090.html",
    "product_name": "スライド式ハサミ（1本）",
    "product_price": 870,
    "product_date": "2024.4.23",
    "product_image": "https://www.family.co.jp/content/dam/family/goods/7820090.jpg"
  },
  {
    "product_url": "https://www.family.co.jp/goods/cw/7820083.html",
    "product_name": "カッター ナイフ（1本）",
    "product_price": 548,
    "product_date": "2024.4.23",
    "product_image": "https://www.family.co.jp/content/dam/family/goods/7820083.jpg"
  },
  {
    "product_url": "https://www.family.co.jp/goods/cw/7810879.html",
    "product_name": "カドがたくさんある消しゴム（3色 各1個入り）",
    "product_price": 348,
    "product_date": "2024.4.23",
    "product_image": "https://www.family.co.jp/content/dam/family/goods/7810879.jpg"
  },
  {
    "product_url": "https://www.family.co.jp/goods/cw/7810886.html",
    "product_name": "ラインソックス消しゴム（1個）",
    "product_price": 280,
    "product_date": "2024.4.23",
    "product_image": "https://www.family.co.jp/content/dam/family/goods/7810886.jpg"
  },
  {
    "product_url": "https://www.family.co.jp/goods/cw/7820052.html",
    "product_name": "ホッチキス（1個）",
    "product_price": 698,
    "product_date": "2024.4.23",
    "product_image": "https://www.family.co.jp/content/dam/family/goods/7820052.jpg"
  },
  {
    "product_url": "https://www.family.co.jp/goods/cw/7820076.html",
    "product_name": "針なしホッチキス（1個）",
    "product_price": 878,
    "product_date": "2024.4.23",
    "product_image": "https://www.family.co.jp/content/dam/family/goods/7820076.jpg"
  },
  {
    "product_url": "https://www.family.co.jp/goods/cw/7820045.html",
    "product_name": "スティックのり（1個）",
    "product_price": 298,
    "product_date": "2024.4.23",
    "product_image": "https://www.family.co.jp/content/dam/family/goods/7820045.jpg"
  },
  {
    "product_url": "https://www.family.co.jp/goods/cw/7820038.html",
    "product_name": "液体のり（1個）",
    "product_price": 248,
    "product_date": "2024.4.23",
    "product_image": "https://www.family.co.jp/content/dam/family/goods/7820038.jpg"
  },
  {
    "product_url": "https://www.family.co.jp/goods/cw/7820021.html",
    "product_name": "テープのり（1個）",
    "product_price": 348,
    "product_date": "2024.4.23",
    "product_image": "https://www.family.co.jp/content/dam/family/goods/7820021.jpg"
  },
  {
    "product_url": "https://www.family.co.jp/goods/cw/7810824.html",
    "product_name": "ゲルインクボールペン 白（1本）",
    "product_price": 198,
    "product_date": "2024.4.23",
    "product_image": "https://www.family.co.jp/content/dam/family/goods/7810824.jpg"
  },
  {
    "product_url": "https://www.family.co.jp/goods/cw/7810817.html",
    "product_name": "ゲルインクボールペン グレー（1本）",
    "product_price": 198,
    "product_date": "2024.4.23",
    "product_image": "https://www.family.co.jp/content/dam/family/goods/7810817.jpg"
  },
  {
    "product_url": "https://www.family.co.jp/goods/cw/7810770.html",
    "product_name": "シャープペンシル　白（1本）",
    "product_price": 198,
    "product_date": "2024.4.23",
    "product_image": "https://www.family.co.jp/content/dam/family/goods/7810770.jpg"
  },
  {
    "product_url": "https://www.family.co.jp/goods/cw/7810831.html",
    "product_name": "2WAYマーカー　ピンク（1本）",
    "product_price": 198,
    "product_date": "2024.4.23",
    "product_image": "https://www.family.co.jp/content/dam/family/goods/7810831.jpg"
  },
  {
    "product_url": "https://www.family.co.jp/goods/cw/7810848.html",
    "product_name": "2WAYマーカー　イエロー（1本）",
    "product_price": 198,
    "product_date": "2024.4.23",
    "product_image": "https://www.family.co.jp/content/dam/family/goods/7810848.jpg"
  },
  {
    "product_url": "https://www.family.co.jp/goods/cw/7810855.html",
    "product_name": "2WAYマーカー　ブルー（1本）",
    "product_price": 198,
    "product_date": "2024.4.23",
    "product_image": "https://www.family.co.jp/content/dam/family/goods/7810855.jpg"
  },
  {
    "product_url": "https://www.family.co.jp/goods/cw/7810862.html",
    "product_name": "2WAYマーカー　グリーン（1本）",
    "product_price": 198,
    "product_date": "2024.4.23",
    "product_image": "https://www.family.co.jp/content/dam/family/goods/7810862.jpg"
  },
  {
    "product_url": "https://www.family.co.jp/goods/cw/7810893.html",
    "product_name": "マーカーセット　空と時間（5色入り）",
    "product_price": 990,
    "product_date": "2024.4.23",
    "product_image": "https://www.family.co.jp/content/dam/family/goods/7810893.jpg"
  },
  {
    "product_url": "https://www.family.co.jp/goods/cw/7831003.html",
    "product_name": "キャンパス綴じノート　A6　B罫（1冊）",
    "product_price": 178,
    "product_date": "2024.4.23",
    "product_image": "https://www.family.co.jp/content/dam/family/goods/7831003.jpg"
  },
  {
    "product_url": "https://www.family.co.jp/goods/cw/7831027.html",
    "product_name": "キャンパス綴じノート　A6　方眼（1冊）",
    "product_price": 178,
    "product_date": "2024.4.23",
    "product_image": "https://www.family.co.jp/content/dam/family/goods/7831027.jpg"
  },
  {
    "product_url": "https://www.family.co.jp/goods/cw/7831041.html",
    "product_name": "キャンパスソフトリングノート　A6　方眼（1冊）",
    "product_price": 338,
    "product_date": "2024.4.23",
    "product_image": "https://www.family.co.jp/content/dam/family/goods/7831041.jpg"
  },
  {
    "product_url": "https://www.family.co.jp/goods/cw/7831058.html",
    "product_name": "キャンパスリングメモ　A7　B罫（1冊）",
    "product_price": 228,
    "product_date": "2024.4.23",
    "product_image": "https://www.family.co.jp/content/dam/family/goods/7831058.jpg"
  },
  {
    "product_url": "https://www.family.co.jp/goods/cw/7831065.html",
    "product_name": "キャンパスリングメモ　A7　方眼（1冊）",
    "product_price": 228,
    "product_date": "2024.4.23",
    "product_image": "https://www.family.co.jp/content/dam/family/goods/7831065.jpg"
  },
  {
    "product_url": "https://www.family.co.jp/goods/cw/7831072.html",
    "product_name": "キャンパスメモパッド　B7　無地（1冊）",
    "product_price": 168,
    "product_date": "2024.4.23",
    "product_image": "https://www.family.co.jp/content/dam/family/goods/7831072.jpg"
  },
  {
    "product_url": "https://www.family.co.jp/goods/cw/7831140.html",
    "product_name": "キャンパス綴じノート　A6　B罫　ファミリーマート（1冊）",
    "product_price": 178,
    "product_date": "2024.4.23",
    "product_image": "https://www.family.co.jp/content/dam/family/goods/7831140.jpg"
  },
  {
    "product_url": "https://www.family.co.jp/goods/cw/7831164.html",
    "product_name": "キャンパス綴じノート　A5　B罫（1冊）",
    "product_price": 218,
    "product_date": "2024.4.23",
    "product_image": "https://www.family.co.jp/content/dam/family/goods/7831164.jpg"
  },
  {
    "product_url": "https://www.family.co.jp/goods/cw/7831188.html",
    "product_name": "キャンパスソフトリングノート　A5　B罫（1冊）",
    "product_price": 348,
    "product_date": "2024.4.23",
    "product_image": "https://www.family.co.jp/content/dam/family/goods/7831188.jpg"
  },
  {
    "product_url": "https://www.family.co.jp/goods/cw/7831195.html",
    "product_name": "キャンパスソフトリングノート　A5　方眼（1冊）",
    "product_price": 348,
    "product_date": "2024.4.23",
    "product_image": "https://www.family.co.jp/content/dam/family/goods/7831195.jpg"
  },
  {
    "product_url": "https://www.family.co.jp/goods/cw/7831201.html",
    "product_name": "キャンパスPC前サイズメモ　方眼（1冊）",
    "product_price": 268,
    "product_date": "2024.4.23",
    "product_image": "https://www.family.co.jp/content/dam/family/goods/7831201.jpg"
  },
  {
    "product_url": "https://www.family.co.jp/goods/cw/7831232.html",
    "product_name": "キャンパス綴じノート　B5　B罫　ファミリーマート（1冊）",
    "product_price": 228,
    "product_date": "2024.4.23",
    "product_image": "https://www.family.co.jp/content/dam/family/goods/7831232.jpg"
  },
  {
    "product_url": "https://www.family.co.jp/goods/cw/7831249.html",
    "product_name": "キャンパス綴じノート　B5　A罫（1冊）",
    "product_price": 228,
    "product_date": "2024.4.23",
    "product_image": "https://www.family.co.jp/content/dam/family/goods/7831249.jpg"
  },
  {
    "product_url": "https://www.family.co.jp/goods/cw/7831256.html",
    "product_name": "キャンパス綴じノート　B5　B罫（1冊）",
    "product_price": 228,
    "product_date": "2024.4.23",
    "product_image": "https://www.family.co.jp/content/dam/family/goods/7831256.jpg"
  },
  {
    "product_url": "https://www.family.co.jp/goods/cw/7831423.html",
    "product_name": "キャンパスソフトリングノート　B5　B罫（1冊）",
    "product_price": 358,
    "product_date": "2024.4.23",
    "product_image": "https://www.family.co.jp/content/dam/family/goods/7831423.jpg"
  },
  {
    "product_url": "https://www.family.co.jp/goods/cw/7831430.html",
    "product_name": "キャンパスソフトリングノート　A6　B罫（1冊）",
    "product_price": 338,
    "product_date": "2024.4.23",
    "product_image": "https://www.family.co.jp/content/dam/family/goods/7831430.jpg"
  },
  {
    "product_url": "https://www.family.co.jp/goods/books/6320010.html",
    "product_name": "すみっコぐらし ふわふわおすわりポーチ　全３種",
    "product_price": 289,
    "product_date": "2024.4.26",
    "product_image": "https://www.family.co.jp/content/dam/family/goods/6320010.jpg"
  },
  {
    "product_url": "https://www.family.co.jp/goods/charakuji/7916854.html",
    "product_name": "一番くじ 星のカービィ プププな いちにち☆",
    "product_price": 700,
    "product_date": "2024.4.27",
    "product_image": "https://www.family.co.jp/content/dam/family/goods/7916854.jpg"
  },
  {
    "product_url": "https://www.family.co.jp/goods/charakuji/7923845.html",
    "product_name": "混血のカレコレ　トレーディングアクリルスタンド",
    "product_price": 770,
    "product_date": "2024.4.25",
    "product_image": "https://www.family.co.jp/content/dam/family/goods/7923845.jpg"
  },
  {
    "product_url": "https://www.family.co.jp/goods/charakuji/7923951.html",
    "product_name": "混血のカレコレ　トレーディングスクエア缶バッジ",
    "product_price": 550,
    "product_date": "2024.4.25",
    "product_image": "https://www.family.co.jp/content/dam/family/goods/7923951.jpg"
  }
]