[
  {
    "product_url": "https://www.family.co.jp/goods/omusubi/0411219.html",
    "product_name": "ふんわりたまごの満足オムライスおむすび",
    "product_price": 268,
    "product_date": "2023.11.21",
    "product_image": "https://www.family.co.jp/content/dam/family/goods/0411219.jpg"
  },
  {
    "product_url": "https://www.family.co.jp/goods/omusubi/0411226.html",
    "product_name": "具だくさん！いか天",
    "product_price": 198,
    "product_date": "2023.11.21",
    "product_image": "https://www.family.co.jp/content/dam/family/goods/0411226.jpg"
  },
  {
    "product_url": "https://www.family.co.jp/goods/obento/0614313.html",
    "product_name": "【東海・北陸】大盛350g！特製炒飯",
    "product_price": 498,
    "product_date": "2023.11.21",
    "product_image": "https://www.family.co.jp/content/dam/family/goods/0614313.jpg"
  },
  {
    "product_url": "https://www.family.co.jp/goods/obento/0614306.html",
    "product_name": "香ばし炒めの特製炒飯",
    "product_price": 398,
    "product_date": "2023.11.21",
    "product_image": "https://www.family.co.jp/content/dam/family/goods/0614306.jpg"
  },
  {
    "product_url": "https://www.family.co.jp/goods/obento/0730396.html",
    "product_name": "ふんわりたまごとだしが決め手の親子丼",
    "product_price": 498,
    "product_date": "2023.11.21",
    "product_image": "https://www.family.co.jp/content/dam/family/goods/0730396.jpg"
  },
  {
    "product_url": "https://www.family.co.jp/goods/sushi/0510189.html",
    "product_name": "手巻寿司　サーモンといくら",
    "product_price": 285,
    "product_date": "2023.11.21",
    "product_image": "https://www.family.co.jp/content/dam/family/goods/0510189.jpg"
  },
  {
    "product_url": "https://www.family.co.jp/goods/sushi/0514651.html",
    "product_name": "2種のキンパ",
    "product_price": 498,
    "product_date": "2023.11.21",
    "product_image": "https://www.family.co.jp/content/dam/family/goods/0514651.jpg"
  },
  {
    "product_url": "https://www.family.co.jp/goods/sushi/0514699.html",
    "product_name": "【東北・九州】唐揚巻",
    "product_price": 398,
    "product_date": "2023.11.21",
    "product_image": "https://www.family.co.jp/content/dam/family/goods/0514699.jpg"
  },
  {
    "product_url": "https://www.family.co.jp/goods/sushi/0515061.html",
    "product_name": "岩下の新生姜いなり寿司",
    "product_price": 168,
    "product_date": "2023.11.21",
    "product_image": "https://www.family.co.jp/content/dam/family/goods/0515061.jpg"
  },
  {
    "product_url": "https://www.family.co.jp/goods/sandwich/0910019.html",
    "product_name": "チョコ&ホイップサンド",
    "product_price": 298,
    "product_date": "2023.11.21",
    "product_image": "https://www.family.co.jp/content/dam/family/goods/0910019.jpg"
  },
  {
    "product_url": "https://www.family.co.jp/goods/sandwich/0920070.html",
    "product_name": "2種類のトルティーヤ　タッカルビ風とチャーシュー",
    "product_price": 398,
    "product_date": "2023.11.21",
    "product_image": "https://www.family.co.jp/content/dam/family/goods/0920070.jpg"
  },
  {
    "product_url": "https://www.family.co.jp/goods/bread/1521559.html",
    "product_name": "ロングスティックパン（ハム&マスタード）",
    "product_price": 158,
    "product_date": "2023.11.21",
    "product_image": "https://www.family.co.jp/content/dam/family/goods/1521559.jpg"
  },
  {
    "product_url": "https://www.family.co.jp/goods/bread/1510478.html",
    "product_name": "ミニメロンバターデニッシュ4個入",
    "product_price": 158,
    "product_date": "2023.11.21",
    "product_image": "https://www.family.co.jp/content/dam/family/goods/1510478.jpg"
  },
  {
    "product_url": "https://www.family.co.jp/goods/bread/1522761.html",
    "product_name": "ハムチーズマヨネーズ2個入",
    "product_price": 138,
    "product_date": "2023.11.21",
    "product_image": "https://www.family.co.jp/content/dam/family/goods/1522761.jpg"
  },
  {
    "product_url": "https://www.family.co.jp/goods/bread/1533705.html",
    "product_name": "チョコツイストサンド（カスタード&ホイップ）",
    "product_price": 138,
    "product_date": "2023.11.21",
    "product_image": "https://www.family.co.jp/content/dam/family/goods/1533705.jpg"
  },
  {
    "product_url": "https://www.family.co.jp/goods/bread/1538854.html",
    "product_name": "シュークリームみたいなパン　カスタード&ホイップ",
    "product_price": 140,
    "product_date": "2023.11.21",
    "product_image": "https://www.family.co.jp/content/dam/family/goods/1538854.jpg"
  },
  {
    "product_url": "https://www.family.co.jp/goods/noodle/0812344.html",
    "product_name": "コク旨　ちゃんぽん",
    "product_price": 550,
    "product_date": "2023.11.21",
    "product_image": "https://www.family.co.jp/content/dam/family/goods/0812344.jpg"
  },
  {
    "product_url": "https://www.family.co.jp/goods/noodle/0812351.html",
    "product_name": "ゆず香るあったか鶏塩そうめん",
    "product_price": 399,
    "product_date": "2023.11.21",
    "product_image": "https://www.family.co.jp/content/dam/family/goods/0812351.jpg"
  },
  {
    "product_url": "https://www.family.co.jp/goods/pasta/0821605.html",
    "product_name": "大盛　グリルチキンのガーリックトマトパスタ",
    "product_price": 578,
    "product_date": "2023.11.21",
    "product_image": "https://www.family.co.jp/content/dam/family/goods/0821605.jpg"
  },
  {
    "product_url": "https://www.family.co.jp/goods/salad/1210835.html",
    "product_name": "増量　たんぱく質が摂れる！豚しゃぶのサラダ",
    "product_price": 438,
    "product_date": "2023.11.21",
    "product_image": "https://www.family.co.jp/content/dam/family/goods/1210835.jpg"
  },
  {
    "product_url": "https://www.family.co.jp/goods/salad/1221206.html",
    "product_name": "1/3日分の野菜使用！ビビンバ風パスタサラダ",
    "product_price": 430,
    "product_date": "2023.11.21",
    "product_image": "https://www.family.co.jp/content/dam/family/goods/1221206.jpg"
  },
  {
    "product_url": "https://www.family.co.jp/goods/salad/1211313.html",
    "product_name": "フレッシュ野菜サラダ",
    "product_price": 178,
    "product_date": "2023.11.21",
    "product_image": "https://www.family.co.jp/content/dam/family/goods/1211313.jpg"
  },
  {
    "product_url": "https://www.family.co.jp/goods/sidedishes/1160291.html",
    "product_name": "シュウマイ&甘酢肉団子",
    "product_price": 468,
    "product_date": "2023.11.21",
    "product_image": "https://www.family.co.jp/content/dam/family/goods/1160291.jpg"
  },
  {
    "product_url": "https://www.family.co.jp/goods/sidedishes/1181470.html",
    "product_name": "【東海・北陸】炙り鶏つくねの盛合せ",
    "product_price": 378,
    "product_date": "2023.11.21",
    "product_image": "https://www.family.co.jp/content/dam/family/goods/1181470.jpg"
  },
  {
    "product_url": "https://www.family.co.jp/goods/sidedishes/1181456.html",
    "product_name": "生姜香る！豚生姜焼き",
    "product_price": 448,
    "product_date": "2023.11.21",
    "product_image": "https://www.family.co.jp/content/dam/family/goods/1181456.jpg"
  },
  {
    "product_url": "https://www.family.co.jp/goods/sidedishes/1131734.html",
    "product_name": "蓮根ごぼうサラダ",
    "product_price": 235,
    "product_date": "2023.11.21",
    "product_image": "https://www.family.co.jp/content/dam/family/goods/1131734.jpg"
  },
  {
    "product_url": "https://www.family.co.jp/goods/sidedishes/1131741.html",
    "product_name": "冷たいまま食べる　タルタルチキン南蛮",
    "product_price": 298,
    "product_date": "2023.11.21",
    "product_image": "https://www.family.co.jp/content/dam/family/goods/1131741.jpg"
  },
  {
    "product_url": "https://www.family.co.jp/goods/deli/1063622.html",
    "product_name": "1/2日分野菜使用　玉子と豚肉の野菜包み焼",
    "product_price": 470,
    "product_date": "2023.11.21",
    "product_image": "https://www.family.co.jp/content/dam/family/goods/1063622.jpg"
  },
  {
    "product_url": "https://www.family.co.jp/goods/deli/1022780.html",
    "product_name": "雑穀入り　トマトとチーズのリゾット風スープ",
    "product_price": 468,
    "product_date": "2023.11.21",
    "product_image": "https://www.family.co.jp/content/dam/family/goods/1022780.jpg"
  },
  {
    "product_url": "https://www.family.co.jp/goods/deli/1060737.html",
    "product_name": "たっぷりチーズの焼カレーグラタン",
    "product_price": 498,
    "product_date": "2023.11.21",
    "product_image": "https://www.family.co.jp/content/dam/family/goods/1060737.jpg"
  },
  {
    "product_url": "https://www.family.co.jp/goods/chilleddaily/2840420.html",
    "product_name": "【北海道・東北・関東】シャキシャキ食感のキムチもやし",
    "product_price": 138,
    "product_date": "2023.11.21",
    "product_image": "https://www.family.co.jp/content/dam/family/goods/2840420.jpg"
  },
  {
    "product_url": "https://www.family.co.jp/goods/chilleddaily/2840390.html",
    "product_name": "【北海道・東北・関東】シャキシャキ食感のサラダもやし",
    "product_price": 138,
    "product_date": "2023.11.21",
    "product_image": "https://www.family.co.jp/content/dam/family/goods/2840390.jpg"
  },
  {
    "product_url": "https://www.family.co.jp/goods/dessert/1947045.html",
    "product_name": "あんこと黒みつの生どら焼き（白玉入り）",
    "product_price": 260,
    "product_date": "2023.11.21",
    "product_image": "https://www.family.co.jp/content/dam/family/goods/1947045.jpg"
  },
  {
    "product_url": "https://www.family.co.jp/goods/dessert/1910711.html",
    "product_name": "くちどけ濃厚冬ショコラ",
    "product_price": 210,
    "product_date": "2023.11.21",
    "product_image": "https://www.family.co.jp/content/dam/family/goods/1910711.jpg"
  },
  {
    "product_url": "https://www.family.co.jp/goods/dessert/1951141.html",
    "product_name": "八天堂　冷やして食べるとろけるくりーむパン　チョコレート",
    "product_price": 280,
    "product_date": "2023.11.21",
    "product_image": "https://www.family.co.jp/content/dam/family/goods/1951141.jpg"
  },
  {
    "product_url": "https://www.family.co.jp/goods/roll/0815048.html",
    "product_name": "【東海】味噌煮込み風うどん",
    "product_price": 550,
    "product_date": "2023.11.21",
    "product_image": "https://www.family.co.jp/content/dam/family/goods/0815048.jpg"
  },
  {
    "product_url": "https://www.family.co.jp/goods/roll/0821407.html",
    "product_name": "【関東】ハーブ香る！完熟トマトパスタ（ソイボール入り）",
    "product_price": 530,
    "product_date": "2023.11.21",
    "product_image": "https://www.family.co.jp/content/dam/family/goods/0821407.jpg"
  },
  {
    "product_url": "https://www.family.co.jp/goods/roll/0817165.html",
    "product_name": "【九州】増量　こだわりだしの肉ごぼう天うどん",
    "product_price": 578,
    "product_date": "2023.11.21",
    "product_image": "https://www.family.co.jp/content/dam/family/goods/0817165.jpg"
  },
  {
    "product_url": "https://www.family.co.jp/goods/roll/0927000.html",
    "product_name": "【四国】ホットサンド　石窯パリジャンサンド海老とブロッコリー",
    "product_price": 398,
    "product_date": "2023.11.21",
    "product_image": "https://www.family.co.jp/content/dam/family/goods/0927000.jpg"
  },
  {
    "product_url": "https://www.family.co.jp/goods/roll/0827034.html",
    "product_name": "【九州】増量大盛　豚カルビの塩焼そば",
    "product_price": 550,
    "product_date": "2023.11.21",
    "product_image": "https://www.family.co.jp/content/dam/family/goods/0827034.jpg"
  },
  {
    "product_url": "https://www.family.co.jp/goods/roll/0817158.html",
    "product_name": "【九州】増量　香ばし炒め野菜のちゃんぽん",
    "product_price": 550,
    "product_date": "2023.11.21",
    "product_image": "https://www.family.co.jp/content/dam/family/goods/0817158.jpg"
  },
  {
    "product_url": "https://www.family.co.jp/goods/roll/0411868.html",
    "product_name": "【関東の一部】手巻　めんツナ（辛口）",
    "product_price": 165,
    "product_date": "2023.11.21",
    "product_image": "https://www.family.co.jp/content/dam/family/goods/0411868.jpg"
  },
  {
    "product_url": "https://www.family.co.jp/goods/roll/0617024.html",
    "product_name": "【九州】わかめごはん&みぞれチキンカツ弁当",
    "product_price": 550,
    "product_date": "2023.11.21",
    "product_image": "https://www.family.co.jp/content/dam/family/goods/0617024.jpg"
  },
  {
    "product_url": "https://www.family.co.jp/goods/roll/0814027.html",
    "product_name": "【北海道】函館あじさい監修　塩ラーメン",
    "product_price": 550,
    "product_date": "2023.11.21",
    "product_image": "https://www.family.co.jp/content/dam/family/goods/0814027.jpg"
  },
  {
    "product_url": "https://www.family.co.jp/goods/roll/1030822.html",
    "product_name": "【九州】増量だし香る！大盛とろーりたこ焼き",
    "product_price": 598,
    "product_date": "2023.11.21",
    "product_image": "https://www.family.co.jp/content/dam/family/goods/1030822.jpg"
  },
  {
    "product_url": "https://www.family.co.jp/goods/processed_foods/3811818.html",
    "product_name": "背脂好きに朗報です。なりたけ監修　みそラーメン",
    "product_price": 320,
    "product_date": "2023.11.21",
    "product_image": "https://www.family.co.jp/content/dam/family/goods/3811818.jpg"
  },
  {
    "product_url": "https://www.family.co.jp/goods/processed_foods/4010036.html",
    "product_name": "甘く芳醇な香りドリップコーヒー　モカブレンド",
    "product_price": 300,
    "product_date": "2023.11.21",
    "product_image": "https://www.family.co.jp/content/dam/family/goods/4010036.jpg"
  },
  {
    "product_url": "https://www.family.co.jp/goods/snack/4723608.html",
    "product_name": "クリート　地球の歩き方グミ　台湾編",
    "product_price": 178,
    "product_date": "2023.11.21",
    "product_image": "https://www.family.co.jp/content/dam/family/goods/4723608.jpg"
  },
  {
    "product_url": "https://www.family.co.jp/goods/snack/4730286.html",
    "product_name": "サクマ　いちごみるくビターチョコがけ",
    "product_price": 182,
    "product_date": "2023.11.21",
    "product_image": "https://www.family.co.jp/content/dam/family/goods/4730286.jpg"
  },
  {
    "product_url": "https://www.family.co.jp/goods/snack/4747161.html",
    "product_name": "クリート　地球の歩き方チョコ　イタリア編",
    "product_price": 213,
    "product_date": "2023.11.21",
    "product_image": "https://www.family.co.jp/content/dam/family/goods/4747161.jpg"
  },
  {
    "product_url": "https://www.family.co.jp/goods/alcohol/5811663.html",
    "product_name": "シャトー・デュ・ラゴン　750ml",
    "product_price": 1078,
    "product_date": "2023.11.21",
    "product_image": "https://www.family.co.jp/content/dam/family/goods/5811663.jpg"
  },
  {
    "product_url": "https://www.family.co.jp/goods/frozen_foods/3520963.html",
    "product_name": "焼いてる！こてっちゃん　岩塩&ペッパー味",
    "product_price": 338,
    "product_date": "2023.11.21",
    "product_image": "https://www.family.co.jp/content/dam/family/goods/3520963.jpg"
  },
  {
    "product_url": "https://www.family.co.jp/goods/frozen_foods/3532805.html",
    "product_name": "たっぷり野菜のにんにくまぜそば",
    "product_price": 438,
    "product_date": "2023.11.21",
    "product_image": "https://www.family.co.jp/content/dam/family/goods/3532805.jpg"
  },
  {
    "product_url": "https://www.family.co.jp/goods/ice/3450918.html",
    "product_name": "フローズンヨーグルト　栃木県産とちあいか使用",
    "product_price": 189,
    "product_date": "2023.11.21",
    "product_image": "https://www.family.co.jp/content/dam/family/goods/3450918.jpg"
  },
  {
    "product_url": "https://www.family.co.jp/goods/ice/3463086.html",
    "product_name": "赤城　たべる牧場ミルクサンド",
    "product_price": 218,
    "product_date": "2023.11.21",
    "product_image": "https://www.family.co.jp/content/dam/family/goods/3463086.jpg"
  },
  {
    "product_url": "https://www.family.co.jp/goods/books/6329440.html",
    "product_name": "すみっコぐらし キルティングバッグ（BLACK ver.・BEIGE ver.）",
    "product_price": 3289,
    "product_date": "2023.11.27",
    "product_image": "https://www.family.co.jp/content/dam/family/goods/6329440.jpg"
  },
  {
    "product_url": "https://www.family.co.jp/goods/books/6329457.html",
    "product_name": "MOOMIN いろいろ使える！便利な折りたたみテーブルBOOK BROWN ver.",
    "product_price": 3069,
    "product_date": "2023.11.24",
    "product_image": "https://www.family.co.jp/content/dam/family/goods/6329457.jpg"
  },
  {
    "product_url": "https://www.family.co.jp/goods/charakuji/7912504.html",
    "product_name": "サンリオくじ「JOCHUM（ジェオチャム）当りくじ」",
    "product_price": 990,
    "product_date": "2023.11.25",
    "product_image": "https://www.family.co.jp/content/dam/family/goods/7912504.jpg"
  },
  {
    "product_url": "https://www.family.co.jp/goods/charakuji/7910852.html",
    "product_name": "一番くじ 映画 すみっコぐらし ツギハギ工場のふしぎなコ",
    "product_price": 680,
    "product_date": "2023.11.25",
    "product_image": "https://www.family.co.jp/content/dam/family/goods/7910852.jpg"
  },
  {
    "product_url": "https://www.family.co.jp/goods/charakuji/7927614.html",
    "product_name": "ちいかわ　リップクリーム",
    "product_price": 550,
    "product_date": "2023.11.22",
    "product_image": "https://www.family.co.jp/content/dam/family/goods/7927614.jpg"
  },
  {
    "product_url": "https://www.family.co.jp/goods/charakuji/7927652.html",
    "product_name": "ちいかわ　ハンドクリーム",
    "product_price": 550,
    "product_date": "2023.11.22",
    "product_image": "https://www.family.co.jp/content/dam/family/goods/7927652.jpg"
  },
  {
    "product_url": "https://www.family.co.jp/goods/charakuji/7927669.html",
    "product_name": "mofusand　リップクリーム",
    "product_price": 550,
    "product_date": "2023.11.22",
    "product_image": "https://www.family.co.jp/content/dam/family/goods/7927669.jpg"
  },
  {
    "product_url": "https://www.family.co.jp/goods/charakuji/7927799.html",
    "product_name": "mofusand　ハンドクリーム",
    "product_price": 550,
    "product_date": "2023.11.22",
    "product_image": "https://www.family.co.jp/content/dam/family/goods/7927799.jpg"
  },
  {
    "product_url": "https://www.family.co.jp/goods/charakuji/7926457.html",
    "product_name": "トミカプレミアム　2023年11月",
    "product_price": 935,
    "product_date": "2023.11.22",
    "product_image": "https://www.family.co.jp/content/dam/family/goods/7926457.jpg"
  }
]